_version.py
hexcover/__init__.py
hexcover/util.py
hexcover-0.6.0.dist-info/METADATA
hexcover-0.6.0.dist-info/WHEEL
hexcover-0.6.0.dist-info/top_level.txt
hexcover-0.6.0.dist-info/RECORD
