Metadata-Version: 2.1
Name: hexcover
Version: 0.6.0
Summary: Given a centroid and side length, tile an area with regular flat hexagons
Author-email: Stephan Hügel <urschrei@gmail.com>
License: # Blue Oak Model License
Project-URL: Repository, https://github.com/urschrei/hexcover
Project-URL: Tracker, https://github.com/urschrei/hexcover/issues
Keywords: Geo,Telecoms,Hexagon,GIS
Classifier: Programming Language :: Python
Classifier: Programming Language :: Python :: 3.8
Classifier: Programming Language :: Python :: 3.9
Classifier: Programming Language :: Python :: 3.10
Classifier: Programming Language :: Python :: 3.11
Classifier: Development Status :: 5 - Production/Stable
Classifier: Intended Audience :: Developers
Classifier: Intended Audience :: Science/Research
Classifier: Intended Audience :: Education
Classifier: Operating System :: OS Independent
Classifier: Topic :: Software Development :: Libraries :: Python Modules
Classifier: Topic :: Scientific/Engineering :: GIS
Requires-Python: >=3.8
Requires-Dist: numpy >=1.11.0
Requires-Dist: shapely >=1.7.0
Provides-Extra: test
Requires-Dist: pytest >=7.4.2 ; extra == 'test'
